illallangi/data/fitness/__init__.py
illallangi/data/fitness/__version__.py
illallangi/data/fitness/apps.py
illallangi/data/fitness/adapters/__init__.py
illallangi/data/fitness/adapters/fitness.py
illallangi/data/fitness/admin/__init__.py
illallangi/data/fitness/admin/swim.py
illallangi/data/fitness/checks/__init__.py
illallangi/data/fitness/checks/fitness.py
illallangi/data/fitness/checks/mastodon.py
illallangi/data/fitness/diffsyncmodels/__init__.py
illallangi/data/fitness/diffsyncmodels/swim.py
illallangi/data/fitness/migrations/0001_initial.py
illallangi/data/fitness/migrations/__init__.py
illallangi/data/fitness/models/__init__.py
illallangi/data/fitness/models/swim.py
illallangi/data/fitness/static/fitness/swims.png
illallangi/data/fitness/templates/fitness/swim_detail.html
illallangi/data/fitness/templates/fitness/swim_list.html
illallangi/data/fitness/views/__init__.py
illallangi/data/fitness/views/swim_detail.py
illallangi/data/fitness/views/swim_list.py
illallangi_data_fitness-0.5.0.dist-info/METADATA
illallangi_data_fitness-0.5.0.dist-info/WHEEL
illallangi_data_fitness-0.5.0.dist-info/entry_points.txt
illallangi_data_fitness-0.5.0.dist-info/licenses/LICENSE
illallangi_data_fitness-0.5.0.dist-info/RECORD
